Metadata-Version: 2.1
Name: jsql-django
Version: 1.0.0
Summary: JSQL backend plugin for Django app
Home-page: https://www.jsql.it
Author: JSQL Sp. z o.o.
Author-email: office@jsql.it
License: UNKNOWN
Platform: UNKNOWN
Classifier: Programming Language :: Python :: 3
Classifier: License :: OSI Approved :: MIT License
Classifier: Operating System :: OS Independent
